setup.cfg
setup.py
DecipherAPI/__init__.py
DecipherAPI/client.py
DecipherAPI.egg-info/PKG-INFO
DecipherAPI.egg-info/SOURCES.txt
DecipherAPI.egg-info/dependency_links.txt
DecipherAPI.egg-info/entry_points.txt
DecipherAPI.egg-info/requires.txt
DecipherAPI.egg-info/top_level.txt