Metadata-Version: 1.1
Name: DecipherAPI
Version: 0.103
Summary: A Python client for Decipher's Beacon API
Home-page: http://www.incontextsolutions.com/
Author: InContext Solutions
Author-email: quant@incontextsolutions.com
License: UNKNOWN
Download-URL: https://github.com/InContextSolutions/Decipher/tarball/v0.1
Keywords: Decipher,survey
Platform: UNKNOWN
